malbolge/__init__.py
malbolge/__main__.py
malbolge/debug_cli.py
malbolge/debug_tui.py
malbolge/debugger.py
malbolge/malbolge.py
malbolge-0.1.0.dist-info/METADATA
malbolge-0.1.0.dist-info/WHEEL
malbolge-0.1.0.dist-info/entry_points.txt
malbolge-0.1.0.dist-info/licenses/LICENSE
malbolge-0.1.0.dist-info/RECORD
