Metadata-Version: 2.4
Name: malbolge
Version: 0.1.0
Summary: Simple Malbolge(https://en.wikipedia.org/wiki/Malbolge) interpreter in python with debugger
Project-URL: Homepage, https://github.com/Aiaid/pyMalbolge
Project-URL: Issues, https://github.com/Aiaid/pyMalbolge/issues
Author-email: Anend <anend@live.com>
License-Expression: MIT
License-File: LICENSE
Classifier: Operating System :: OS Independent
Classifier: Programming Language :: Python :: 3
Requires-Python: >=3.8
Provides-Extra: dev
Requires-Dist: pytest; extra == 'dev'
Requires-Dist: textual>=0.40.0; extra == 'dev'
Provides-Extra: tui
Requires-Dist: textual>=0.40.0; extra == 'tui'
